LICENSE
MANIFEST.in
README.md
setup.py
jsdhgsdysdhggds/__init__.py
jsdhgsdysdhggds/api_helper.py
jsdhgsdysdhggds/configuration.py
jsdhgsdysdhggds/decorators.py
jsdhgsdysdhggds/jsdhgsdysdhggds_client.py
jsdhgsdysdhggds.egg-info/PKG-INFO
jsdhgsdysdhggds.egg-info/SOURCES.txt
jsdhgsdysdhggds.egg-info/dependency_links.txt
jsdhgsdysdhggds.egg-info/requires.txt
jsdhgsdysdhggds.egg-info/top_level.txt
jsdhgsdysdhggds/controllers/__init__.py
jsdhgsdysdhggds/controllers/api_controller.py
jsdhgsdysdhggds/controllers/base_controller.py
jsdhgsdysdhggds/exceptions/__init__.py
jsdhgsdysdhggds/exceptions/api_exception.py
jsdhgsdysdhggds/http/__init__.py
jsdhgsdysdhggds/http/http_call_back.py
jsdhgsdysdhggds/http/http_client.py
jsdhgsdysdhggds/http/http_context.py
jsdhgsdysdhggds/http/http_method_enum.py
jsdhgsdysdhggds/http/http_request.py
jsdhgsdysdhggds/http/http_response.py
jsdhgsdysdhggds/http/requests_client.py
jsdhgsdysdhggds/http/auth/__init__.py
jsdhgsdysdhggds/http/auth/basic_auth.py
jsdhgsdysdhggds/models/__init__.py
jsdhgsdysdhggds/models/suite_code_enum.py
tests/__init__.py
tests/http_response_catcher.py
tests/test_helper.py
tests/controllers/__init__.py
tests/controllers/controller_test_base.py
tests/controllers/test_api_controller.py