Metadata-Version: 1.0
Name: jsdhgsdysdhggds
Version: 1.1
Summary: TODO: add library description
Home-page: https://apimatic.io
Author: APIMatic SDK Generator
Author-email: support@apimatic.io
License: UNKNOWN
Platform: UNKNOWN
